autodocsumm/__init__.py
autodocsumm/_version.py
autodocsumm-0.2.14.dist-info/LICENSE
autodocsumm-0.2.14.dist-info/METADATA
autodocsumm-0.2.14.dist-info/WHEEL
autodocsumm-0.2.14.dist-info/top_level.txt
autodocsumm-0.2.14.dist-info/RECORD
