Metadata-Version: 2.1
Name: autodocsumm
Version: 0.2.14
Summary: Extended sphinx autodoc including automatic autosummaries
Author-email: "Philipp S. Sommer" <philipp.sommer@hereon.de>
License: Apache-2.0
Project-URL: Homepage, https://github.com/Chilipp/autodocsumm
Project-URL: Documentation, https://autodocsumm.readthedocs.io/en/latest/
Project-URL: Source, https://github.com/Chilipp/autodocsumm
Project-URL: Tracker, https://github.com/Chilipp/autodocsumm/issues
Keywords: sphinx,autodoc,autosummary,content,table
Classifier: Development Status :: 5 - Production/Stable
Classifier: Intended Audience :: Developers
Classifier: Topic :: Documentation
Classifier: License :: OSI Approved :: Apache Software License
Classifier: Framework :: Sphinx
Classifier: Framework :: Sphinx :: Extension
Classifier: Programming Language :: Python :: 3
Classifier: Programming Language :: Python :: 3 :: Only
Classifier: Programming Language :: Python :: 3.7
Classifier: Programming Language :: Python :: 3.8
Classifier: Programming Language :: Python :: 3.9
Classifier: Programming Language :: Python :: 3.10
Classifier: Programming Language :: Python :: 3.11
Classifier: Programming Language :: Python :: 3.12
Classifier: Operating System :: OS Independent
Requires-Python: >=3.7
License-File: LICENSE
Requires-Dist: Sphinx<9.0,>=4.0
